tsconcat/__init__.py
tsconcat/tsconcat.py
tsconcat/utils.py
tsconcat-0.1.0.dist-info/LICENSE
tsconcat-0.1.0.dist-info/METADATA
tsconcat-0.1.0.dist-info/WHEEL
tsconcat-0.1.0.dist-info/RECORD
