Metadata-Version: 2.1
Name: tsconcat
Version: 0.1.0
Summary: A tool for joining multiple, homogeneous tensorstore datasets using the N5 driver into a single dataset.
License: MIT
Author: Luis Herrmann
Requires-Python: >=3.8,<4.0
Classifier: License :: OSI Approved :: MIT License
Classifier: Programming Language :: Python :: 3
Classifier: Programming Language :: Python :: 3.8
Classifier: Programming Language :: Python :: 3.9
Classifier: Programming Language :: Python :: 3.10
Classifier: Programming Language :: Python :: 3.11
Requires-Dist: addict (>=2.4.0,<3.0.0)
Requires-Dist: numpy (>=1.22.0,<2.0.0)
Requires-Dist: taskipy (>=1.10.3,<2.0.0)
Requires-Dist: tensorstore (>=0.1.33,<0.2.0)
Requires-Dist: tqdm (>=4.65.0,<5.0.0)
